README.md
setup.py
xiaohongshu/__init__.py
xiaohongshu.egg-info/PKG-INFO
xiaohongshu.egg-info/SOURCES.txt
xiaohongshu.egg-info/dependency_links.txt
xiaohongshu.egg-info/requires.txt
xiaohongshu.egg-info/top_level.txt
xiaohongshu.egg-info/zip-safe
xiaohongshu/api/__init__.py
xiaohongshu/api/api.py
xiaohongshu/api/comApi.py
xiaohongshu/api/comm.py
xiaohongshu/api/const.py
xiaohongshu/api/exceptions.py
xiaohongshu/api/orderApi.py
xiaohongshu/api/productApi.py
xiaohongshu/api/stockApi.py
xiaohongshu/tests/__init__.py
xiaohongshu/tests/test_sign.py